{
  "transformers": [
    {
      "name": "num",
      "columns": [
        "age",
        "dialysis_age",
        "hb",
        "albumin",
        "crp",
        "pth",
        "calcium",
        "phosphorus",
        "potassium",
        "sodium",
        "creatinine",
        "ktv",
        "urr",
        "dry_weight",
        "esa_dose",
        "esa_use_flag",
        "iron_use_flag",
        "hif_use_flag",
        "eq_esa_dose",
        "eri",
        "ferritin_mean",
        "tsat_mean",
        "log_ferritin",
        "ferritin_deficiency",
        "tsat_deficiency",
        "ferritin_crp_interaction",
        "ferritin_missing",
        "tsat_missing",
        "pre_sbp_q1_mean",
        "pre_sbp_q1_std",
        "pre_dbp_q1_mean",
        "pre_dbp_q1_std",
        "idh_count_q1",
        "idh_any_q1",
        "pre_sbp_q2_mean",
        "pre_dbp_q2_mean",
        "idh_any_q2",
        "pre_sbp_q3_mean",
        "pre_dbp_q3_mean",
        "idh_any_q3",
        "delta_hb",
        "delta_esa_dose",
        "delta_eri",
        "delta_crp",
        "delta_albumin",
        "delta_ktv",
        "delta_pth",
        "delta_ferritin_mean",
        "delta_tsat_mean",
        "prior_low_response_proxy"
      ],
      "steps": [
        {
          "imputer": {
            "type": "SimpleImputer",
            "strategy": "median",
            "statistics_": [
              60.0,
              40.0,
              111.0,
              39.3,
              2.9,
              226.0,
              2.22,
              2.0,
              4.79,
              137.5,
              977.05,
              1.39,
              69.23,
              56.1,
              10000.0,
              1.0,
              1.0,
              0.0,
              6666.666666666667,
              12.037136851964064,
              80.0,
              24.14,
              4.394449154672439,
              1.0,
              0.0,
              12.390979207495088,
              0.0,
              0.0,
              145.0,
              5.557777333511022,
              82.66666666666667,
              4.08248290463863,
              0.0,
              0.0,
              142.0,
              82.0,
              0.0,
              140.33333333333334,
              81.0,
              0.0,
              1.0,
              0.0,
              -0.12657098302901026,
              0.0,
              -0.20000000000000284,
              -0.0024999999999999467,
              3.6000000000000014,
              0.0,
              0.0,
              0.0
            ]
          }
        },
        {
          "scaler": {
            "type": "StandardScaler",
            "mean_": [
              59.252549651100374,
              50.762748255501876,
              109.77181964573269,
              39.08181427804616,
              6.534151637144392,
              304.4399560118089,
              2.275917606011809,
              2.04227321524423,
              4.833888888888889,
              137.4474074074074,
              985.000397208803,
              1.4128115942028987,
              60.23393451422437,
              56.819055287171224,
              10158.29307568438,
              1.0,
              0.5407944176060118,
              0.177938808373591,
              7832.903918411164,
              13.712206885477727,
              147.3923532832349,
              26.150977589908745,
              4.443006843066252,
              0.621309715512614,
              0.22839506172839505,
              29.288263873907148,
              0.09554482018250134,
              0.2944176060118089,
              145.04781714081233,
              5.898281124177794,
              82.75116299874753,
              4.231148844471307,
              0.01878690284487386,
              0.011003757380568975,
              142.10207550545712,
              82.05810520665594,
              0.015029522275899088,
              140.33735909822866,
              81.04159957058508,
              0.014224369296833066,
              1.5380568974771873,
              -26.81159420289855,
              -0.3480344638549958,
              -0.3810670960815889,
              -0.12447665056360845,
              -0.0007584541062801667,
              1.3356522544283422,
              0.0,
              0.0,
              0.10010735373054214
            ],
            "scale_": [
              12.572018521262097,
              39.68458664171447,
              18.108418941774026,
              3.9391821785795536,
              19.47641450434521,
              313.7964015725299,
              3.137774468653101,
              0.7758283447186212,
              0.7217770738883077,
              4.084342783489442,
              379.78837081354914,
              0.8579099701240214,
              491.5442854517906,
              10.189510081140753,
              4626.863227248145,
              1.0,
              0.4983330367256281,
              0.38246122528718834,
              4127.850088538223,
              8.681766666463483,
              382.7114930218093,
              10.778873120358806,
              0.9698539796286096,
              0.48506077240099377,
              0.41979847249183466,
              108.31307944342244,
              0.2939659972153154,
              0.45578051656700314,
              8.323591685181384,
              2.65508293332616,
              5.1905046030540065,
              1.6338947687411194,
              0.1970562455985017,
              0.10432005897275247,
              8.444918686616864,
              5.492860224799176,
              0.12167019247152257,
              8.50271052408517,
              5.439686673651695,
              0.11841468074077802,
              13.438901156218753,
              1899.8411890672949,
              3.9586028981544423,
              16.49674455169479,
              2.893701293114136,
              0.8225188008183134,
              175.0282924769786,
              1.0,
              1.0,
              0.3001430849771659
            ]
          }
        }
      ]
    },
    {
      "name": "cat",
      "columns": [
        "center_creator",
        "receiving_center",
        "sex",
        "patient_status",
        "primary_disease",
        "esa_use",
        "esa_route",
        "esa_unit",
        "esa_type",
        "iron_use",
        "hif_use"
      ],
      "steps": [
        {
          "imputer": {
            "type": "SimpleImputer",
            "strategy": "most_frequent",
            "statistics_": [
              "\u6cb3\u6e90\u5e02\u7d2b\u91d1\u53bf\u4e2d\u533b\u9662\u8840\u900f\u4e2d\u5fc3",
              "\u4e0d\u8be6",
              "\u7537",
              "\u5728\u900f",
              "\u539f\u53d1\u75c5\u4e0d\u660e\u786e",
              "\u4f7f\u7528",
              "\u9759\u8109",
              "IU",
              "\u91cd\u7ec4\u4eba\u4fc3\u7ea2\u7ec6\u80de\u751f\u6210\u7d20\uff08rHuEPO\uff09",
              "\u4f7f\u7528",
              "\u672a\u4f7f\u7528"
            ]
          }
        },
        {
          "encoder": {
            "type": "OneHotEncoder",
            "categories_": [
              [
                "\u4e1c\u6e90\u53bf\u8239\u5858\u4e2d\u5fc3\u536b\u751f\u9662\u8840\u900f\u5ba4",
                "\u53f6\u745e\u5c71",
                "\u548c\u5e73\u897f\u90ca\u533b\u9662",
                "\u5f90\u80b2\u68ee",
                "\u674f\u674f",
                "\u6cb3\u6e90\u4e2d\u6b63\u8840\u6db2\u900f\u6790\u4e2d\u5fc3",
                "\u6cb3\u6e90\u4ec1\u5eb7\u8840\u6db2\u900f\u6790\u4e2d\u5fc3\u6709\u9650\u516c\u53f8",
                "\u6cb3\u6e90\u534e\u4fe1\u6cf0\u5eb7\u533b\u9662\u8840\u900f\u5ba4",
                "\u6cb3\u6e90\u53cb\u597d\u533b\u9662",
                "\u6cb3\u6e90\u5e02\u4e1c\u6e90\u53bf\u4e2d\u533b\u9662\u8840\u900f\u5ba4",
                "\u6cb3\u6e90\u5e02\u4e1c\u6e90\u53bf\u4eba\u6c11\u533b\u9662\u8840\u900f\u5ba4",
                "\u6cb3\u6e90\u5e02\u4e2d\u533b\u9662\u8840\u900f\u4e2d\u5fc3",
                "\u6cb3\u6e90\u5e02\u4eba\u6c11\u533b\u9662\u8840\u900f\u4e2d\u5fc3",
                "\u6cb3\u6e90\u5e02\u548c\u5e73\u53bf\u4e2d\u533b\u9662\u65b0\u9662\u8840\u900f\u5ba4",
                "\u6cb3\u6e90\u5e02\u548c\u5e73\u53bf\u4eba\u6c11\u533b\u9662\u8840\u900f\u4e2d\u5fc3",
                "\u6cb3\u6e90\u5e02\u6df1\u6cb3\u4eba\u6c11\u533b\u9662\uff08\u66a8\u5357\u5927\u5b66\u9644\u5c5e\u7b2c\u4e94\u533b\u9662\uff09",
                "\u6cb3\u6e90\u5e02\u6e90\u57ce\u533a\u4e1c\u57d4\u793e\u533a\u536b\u751f\u670d\u52a1\u4e2d\u5fc3\uff08\u6cb3\u6e90\u4e1c\u57d4\u533b\u9662\uff09\u8840\u900f\u5ba4",
                "\u6cb3\u6e90\u5e02\u6e90\u57ce\u533a\u4eba\u6c11\u533b\u9662\u8840\u900f\u4e2d\u5fc3",
                "\u6cb3\u6e90\u5e02\u7d2b\u91d1\u53bf\u4e2d\u533b\u9662\u8840\u900f\u4e2d\u5fc3",
                "\u6cb3\u6e90\u5e02\u7d2b\u91d1\u53bf\u4eba\u6c11\u533b\u9662\u8840\u900f\u4e2d\u5fc3",
                "\u6cb3\u6e90\u5e02\u8fde\u5e73\u53bf\u7b2c\u4e8c\u4eba\u6c11\u533b\u9662\u8840\u900f\u4e2d\u5fc3",
                "\u6cb3\u6e90\u5e02\u9f99\u5ddd\u53bf\u4eba\u6c11\u533b\u9662\u8840\u900f\u4e2d\u5fc3",
                "\u6cb3\u6e90\u5fb7\u5eb7\u533b\u9662",
                "\u6cb3\u6e90\u957f\u5b89\u533b\u9662\u8840\u900f\u4e2d\u5fc3",
                "\u6e90\u57ce\u5b9d\u829d\u6797\u4e2d\u533b\u9662",
                "\u7d2b\u91d1\u53bf\u84dd\u5858\u4e2d\u5fc3\u536b\u751f\u9662",
                "\u7d2b\u91d1\u660a\u8fb0\u8840\u6db2\u900f\u6790\u4e2d\u5fc3",
                "\u97f3\u4e50",
                "\u9f99\u5ddd\u53bf\u4e2d\u533b\u9662\u8840\u6db2\u900f\u6790\u5ba4",
                "\u9f99\u5ddd\u53bf\u5987\u5e7c\u4fdd\u5065\u8ba1\u5212\u751f\u80b2\u670d\u52a1\u4e2d\u5fc3",
                "\u9f99\u5ddd\u6c11\u6d4e\u8840\u6db2\u900f\u6790\u4e2d\u5fc3"
              ],
              [
                "/",
                "\u4e0d\u8be6",
                "\u4e2d\u5c71\u5927\u5b66\u7b2c\u4e00\u9644\u5c5e\u533b\u9662",
                "\u4e2d\u6b63\u8840\u6db2\u900f\u6790\u4e2d\u5fc3",
                "\u4e2d\u6b63\u8840\u900f\u4e2d\u5fc3",
                "\u4eba\u6c11\u533b\u9662",
                "\u548c\u5e73\u53bf\u4e2d\u533b\u9662",
                "\u548c\u5e73\u53bf\u4eba\u6c11\u533b\u9662",
                "\u5b9d\u829d\u6797\u533b\u9662",
                "\u5e7f\u4e1c\u7701\u4e2d\u533b\u9662",
                "\u5f53\u5730\u533b\u9662",
                "\u60e0\u5dde\u5e02\u7b2c\u516d\u4eba\u6c11\u533b\u9662",
                "\u672a\u77e5",
                "\u6885\u5dde\u5e02\u4eba\u6c11\u533b\u9662",
                "\u6c11\u6d4e",
                "\u6c11\u6d4e\u900f\u6790\u4e2d\u5fc3",
                "\u6cb3\u6e90\u5b9d\u829d\u6797\u4e2d\u533b\u9662",
                "\u6cb3\u6e90\u5e02\u4e1c\u57d4\u793e\u533a\u536b\u751f\u670d\u52a1\u4e2d\u5fc3",
                "\u6cb3\u6e90\u5e02\u4e2d\u533b\u9662",
                "\u6cb3\u6e90\u5e02\u4eba\u6c11\u533b\u9662",
                "\u6cb3\u6e90\u5e02\u5fb7\u5eb7\u533b\u9662",
                "\u6d4e\u6c11\u533b\u9662",
                "\u6df1\u6cb3\u4eba\u6c11\u533b\u9662",
                "\u7d2b\u91d1\u53bf\u4e2d\u533b\u9662",
                "\u7d2b\u91d1\u53bf\u6c11\u8425\u8840\u900f",
                "\u8239\u5858\u536b\u751f\u9662",
                "\u957f\u5b89\u533b\u9662",
                "\u9f99\u5ddd\u53bf\u4eba\u6c11\u533b\u9662"
              ],
              [
                "\u5973",
                "\u7537"
              ],
              [
                "\u5176\u5b83",
                "\u5728\u900f",
                "\u597d\u8f6c\u8131\u79bb\u900f\u6790",
                "\u653e\u5f03\u6cbb\u7597\u6216\u5931\u8bbf",
                "\u6b7b\u4ea1",
                "\u8f6c\u5176\u5b83\u900f\u6790\u673a\u6784",
                "\u8f6c\u80be\u79fb\u690d",
                "\u8f6c\u8179\u819c\u900f\u6790"
              ],
              [
                "\u5176\u5b83\u7ee7\u53d1\u6027\u80be\u5c0f\u7403\u75be\u75c5",
                "\u539f\u53d1\u6027\u80be\u5c0f\u7403\u75be\u75c5",
                "\u539f\u53d1\u75c5\u4e0d\u660e\u786e",
                "\u6ccc\u5c3f\u7cfb\u611f\u67d3\u548c\u7ed3\u77f3",
                "\u6ccc\u5c3f\u7cfb\u80bf\u7624",
                "\u7cd6\u5c3f\u75c5\u80be\u75c5",
                "\u80be\u5c0f\u7ba1\u95f4\u8d28\u75be\u75c5",
                "\u80be\u810f\u5207\u9664\u672f\u540e",
                "\u836f\u7269\u6027\u80be\u635f\u5bb3",
                "\u9057\u4f20\u6027\u53ca\u5148\u5929\u6027\u75be\u75c5",
                "\u9ad8\u8840\u538b\u80be\u635f\u5bb3"
              ],
              [
                "\u4f7f\u7528"
              ],
              [
                "\u76ae\u4e0b",
                "\u9759\u8109"
              ],
              [
                "IU"
              ],
              [
                "\u5176\u5b83",
                "\u91cd\u7ec4\u4eba\u4fc3\u7ea2\u7ec6\u80de\u751f\u6210\u7d20\uff08rHuEPO\uff09"
              ],
              [
                "\u4f7f\u7528",
                "\u672a\u4f7f\u7528"
              ],
              [
                "\u4f7f\u7528",
                "\u672a\u4f7f\u7528"
              ]
            ],
            "handle_unknown": "ignore"
          }
        }
      ]
    }
  ],
  "feature_names_out": [
    "num__age",
    "num__dialysis_age",
    "num__hb",
    "num__albumin",
    "num__crp",
    "num__pth",
    "num__calcium",
    "num__phosphorus",
    "num__potassium",
    "num__sodium",
    "num__creatinine",
    "num__ktv",
    "num__urr",
    "num__dry_weight",
    "num__esa_dose",
    "num__esa_use_flag",
    "num__iron_use_flag",
    "num__hif_use_flag",
    "num__eq_esa_dose",
    "num__eri",
    "num__ferritin_mean",
    "num__tsat_mean",
    "num__log_ferritin",
    "num__ferritin_deficiency",
    "num__tsat_deficiency",
    "num__ferritin_crp_interaction",
    "num__ferritin_missing",
    "num__tsat_missing",
    "num__pre_sbp_q1_mean",
    "num__pre_sbp_q1_std",
    "num__pre_dbp_q1_mean",
    "num__pre_dbp_q1_std",
    "num__idh_count_q1",
    "num__idh_any_q1",
    "num__pre_sbp_q2_mean",
    "num__pre_dbp_q2_mean",
    "num__idh_any_q2",
    "num__pre_sbp_q3_mean",
    "num__pre_dbp_q3_mean",
    "num__idh_any_q3",
    "num__delta_hb",
    "num__delta_esa_dose",
    "num__delta_eri",
    "num__delta_crp",
    "num__delta_albumin",
    "num__delta_ktv",
    "num__delta_pth",
    "num__delta_ferritin_mean",
    "num__delta_tsat_mean",
    "num__prior_low_response_proxy",
    "cat__center_creator_\u4e1c\u6e90\u53bf\u8239\u5858\u4e2d\u5fc3\u536b\u751f\u9662\u8840\u900f\u5ba4",
    "cat__center_creator_\u53f6\u745e\u5c71",
    "cat__center_creator_\u548c\u5e73\u897f\u90ca\u533b\u9662",
    "cat__center_creator_\u5f90\u80b2\u68ee",
    "cat__center_creator_\u674f\u674f",
    "cat__center_creator_\u6cb3\u6e90\u4e2d\u6b63\u8840\u6db2\u900f\u6790\u4e2d\u5fc3",
    "cat__center_creator_\u6cb3\u6e90\u4ec1\u5eb7\u8840\u6db2\u900f\u6790\u4e2d\u5fc3\u6709\u9650\u516c\u53f8",
    "cat__center_creator_\u6cb3\u6e90\u534e\u4fe1\u6cf0\u5eb7\u533b\u9662\u8840\u900f\u5ba4",
    "cat__center_creator_\u6cb3\u6e90\u53cb\u597d\u533b\u9662",
    "cat__center_creator_\u6cb3\u6e90\u5e02\u4e1c\u6e90\u53bf\u4e2d\u533b\u9662\u8840\u900f\u5ba4",
    "cat__center_creator_\u6cb3\u6e90\u5e02\u4e1c\u6e90\u53bf\u4eba\u6c11\u533b\u9662\u8840\u900f\u5ba4",
    "cat__center_creator_\u6cb3\u6e90\u5e02\u4e2d\u533b\u9662\u8840\u900f\u4e2d\u5fc3",
    "cat__center_creator_\u6cb3\u6e90\u5e02\u4eba\u6c11\u533b\u9662\u8840\u900f\u4e2d\u5fc3",
    "cat__center_creator_\u6cb3\u6e90\u5e02\u548c\u5e73\u53bf\u4e2d\u533b\u9662\u65b0\u9662\u8840\u900f\u5ba4",
    "cat__center_creator_\u6cb3\u6e90\u5e02\u548c\u5e73\u53bf\u4eba\u6c11\u533b\u9662\u8840\u900f\u4e2d\u5fc3",
    "cat__center_creator_\u6cb3\u6e90\u5e02\u6df1\u6cb3\u4eba\u6c11\u533b\u9662\uff08\u66a8\u5357\u5927\u5b66\u9644\u5c5e\u7b2c\u4e94\u533b\u9662\uff09",
    "cat__center_creator_\u6cb3\u6e90\u5e02\u6e90\u57ce\u533a\u4e1c\u57d4\u793e\u533a\u536b\u751f\u670d\u52a1\u4e2d\u5fc3\uff08\u6cb3\u6e90\u4e1c\u57d4\u533b\u9662\uff09\u8840\u900f\u5ba4",
    "cat__center_creator_\u6cb3\u6e90\u5e02\u6e90\u57ce\u533a\u4eba\u6c11\u533b\u9662\u8840\u900f\u4e2d\u5fc3",
    "cat__center_creator_\u6cb3\u6e90\u5e02\u7d2b\u91d1\u53bf\u4e2d\u533b\u9662\u8840\u900f\u4e2d\u5fc3",
    "cat__center_creator_\u6cb3\u6e90\u5e02\u7d2b\u91d1\u53bf\u4eba\u6c11\u533b\u9662\u8840\u900f\u4e2d\u5fc3",
    "cat__center_creator_\u6cb3\u6e90\u5e02\u8fde\u5e73\u53bf\u7b2c\u4e8c\u4eba\u6c11\u533b\u9662\u8840\u900f\u4e2d\u5fc3",
    "cat__center_creator_\u6cb3\u6e90\u5e02\u9f99\u5ddd\u53bf\u4eba\u6c11\u533b\u9662\u8840\u900f\u4e2d\u5fc3",
    "cat__center_creator_\u6cb3\u6e90\u5fb7\u5eb7\u533b\u9662",
    "cat__center_creator_\u6cb3\u6e90\u957f\u5b89\u533b\u9662\u8840\u900f\u4e2d\u5fc3",
    "cat__center_creator_\u6e90\u57ce\u5b9d\u829d\u6797\u4e2d\u533b\u9662",
    "cat__center_creator_\u7d2b\u91d1\u53bf\u84dd\u5858\u4e2d\u5fc3\u536b\u751f\u9662",
    "cat__center_creator_\u7d2b\u91d1\u660a\u8fb0\u8840\u6db2\u900f\u6790\u4e2d\u5fc3",
    "cat__center_creator_\u97f3\u4e50",
    "cat__center_creator_\u9f99\u5ddd\u53bf\u4e2d\u533b\u9662\u8840\u6db2\u900f\u6790\u5ba4",
    "cat__center_creator_\u9f99\u5ddd\u53bf\u5987\u5e7c\u4fdd\u5065\u8ba1\u5212\u751f\u80b2\u670d\u52a1\u4e2d\u5fc3",
    "cat__center_creator_\u9f99\u5ddd\u6c11\u6d4e\u8840\u6db2\u900f\u6790\u4e2d\u5fc3",
    "cat__receiving_center_/",
    "cat__receiving_center_\u4e0d\u8be6",
    "cat__receiving_center_\u4e2d\u5c71\u5927\u5b66\u7b2c\u4e00\u9644\u5c5e\u533b\u9662",
    "cat__receiving_center_\u4e2d\u6b63\u8840\u6db2\u900f\u6790\u4e2d\u5fc3",
    "cat__receiving_center_\u4e2d\u6b63\u8840\u900f\u4e2d\u5fc3",
    "cat__receiving_center_\u4eba\u6c11\u533b\u9662",
    "cat__receiving_center_\u548c\u5e73\u53bf\u4e2d\u533b\u9662",
    "cat__receiving_center_\u548c\u5e73\u53bf\u4eba\u6c11\u533b\u9662",
    "cat__receiving_center_\u5b9d\u829d\u6797\u533b\u9662",
    "cat__receiving_center_\u5e7f\u4e1c\u7701\u4e2d\u533b\u9662",
    "cat__receiving_center_\u5f53\u5730\u533b\u9662",
    "cat__receiving_center_\u60e0\u5dde\u5e02\u7b2c\u516d\u4eba\u6c11\u533b\u9662",
    "cat__receiving_center_\u672a\u77e5",
    "cat__receiving_center_\u6885\u5dde\u5e02\u4eba\u6c11\u533b\u9662",
    "cat__receiving_center_\u6c11\u6d4e",
    "cat__receiving_center_\u6c11\u6d4e\u900f\u6790\u4e2d\u5fc3",
    "cat__receiving_center_\u6cb3\u6e90\u5b9d\u829d\u6797\u4e2d\u533b\u9662",
    "cat__receiving_center_\u6cb3\u6e90\u5e02\u4e1c\u57d4\u793e\u533a\u536b\u751f\u670d\u52a1\u4e2d\u5fc3",
    "cat__receiving_center_\u6cb3\u6e90\u5e02\u4e2d\u533b\u9662",
    "cat__receiving_center_\u6cb3\u6e90\u5e02\u4eba\u6c11\u533b\u9662",
    "cat__receiving_center_\u6cb3\u6e90\u5e02\u5fb7\u5eb7\u533b\u9662",
    "cat__receiving_center_\u6d4e\u6c11\u533b\u9662",
    "cat__receiving_center_\u6df1\u6cb3\u4eba\u6c11\u533b\u9662",
    "cat__receiving_center_\u7d2b\u91d1\u53bf\u4e2d\u533b\u9662",
    "cat__receiving_center_\u7d2b\u91d1\u53bf\u6c11\u8425\u8840\u900f",
    "cat__receiving_center_\u8239\u5858\u536b\u751f\u9662",
    "cat__receiving_center_\u957f\u5b89\u533b\u9662",
    "cat__receiving_center_\u9f99\u5ddd\u53bf\u4eba\u6c11\u533b\u9662",
    "cat__sex_\u5973",
    "cat__sex_\u7537",
    "cat__patient_status_\u5176\u5b83",
    "cat__patient_status_\u5728\u900f",
    "cat__patient_status_\u597d\u8f6c\u8131\u79bb\u900f\u6790",
    "cat__patient_status_\u653e\u5f03\u6cbb\u7597\u6216\u5931\u8bbf",
    "cat__patient_status_\u6b7b\u4ea1",
    "cat__patient_status_\u8f6c\u5176\u5b83\u900f\u6790\u673a\u6784",
    "cat__patient_status_\u8f6c\u80be\u79fb\u690d",
    "cat__patient_status_\u8f6c\u8179\u819c\u900f\u6790",
    "cat__primary_disease_\u5176\u5b83\u7ee7\u53d1\u6027\u80be\u5c0f\u7403\u75be\u75c5",
    "cat__primary_disease_\u539f\u53d1\u6027\u80be\u5c0f\u7403\u75be\u75c5",
    "cat__primary_disease_\u539f\u53d1\u75c5\u4e0d\u660e\u786e",
    "cat__primary_disease_\u6ccc\u5c3f\u7cfb\u611f\u67d3\u548c\u7ed3\u77f3",
    "cat__primary_disease_\u6ccc\u5c3f\u7cfb\u80bf\u7624",
    "cat__primary_disease_\u7cd6\u5c3f\u75c5\u80be\u75c5",
    "cat__primary_disease_\u80be\u5c0f\u7ba1\u95f4\u8d28\u75be\u75c5",
    "cat__primary_disease_\u80be\u810f\u5207\u9664\u672f\u540e",
    "cat__primary_disease_\u836f\u7269\u6027\u80be\u635f\u5bb3",
    "cat__primary_disease_\u9057\u4f20\u6027\u53ca\u5148\u5929\u6027\u75be\u75c5",
    "cat__primary_disease_\u9ad8\u8840\u538b\u80be\u635f\u5bb3",
    "cat__esa_use_\u4f7f\u7528",
    "cat__esa_route_\u76ae\u4e0b",
    "cat__esa_route_\u9759\u8109",
    "cat__esa_unit_IU",
    "cat__esa_type_\u5176\u5b83",
    "cat__esa_type_\u91cd\u7ec4\u4eba\u4fc3\u7ea2\u7ec6\u80de\u751f\u6210\u7d20\uff08rHuEPO\uff09",
    "cat__iron_use_\u4f7f\u7528",
    "cat__iron_use_\u672a\u4f7f\u7528",
    "cat__hif_use_\u4f7f\u7528",
    "cat__hif_use_\u672a\u4f7f\u7528"
  ]
}